[
  {
    "id": "STMARY",
    "name": "St Mary's Hospital",
    "trust": "Manchester University NHS Foundation Trust",
    "address": "Oxford Rd, Manchester M13 9WL",
    "lat": 53.4628,
    "lon": -2.2256,
    "specialties": ["general", "trauma", "obstetrics", "paediatric"],
    "departments": {
      "trauma":   {"capacity": 10, "patients": 8,  "wait_minutes": 18},
      "cardiac":  {"capacity": 10, "patients": 6,  "wait_minutes": 14},
      "general":  {"capacity": 52, "patients": 28, "wait_minutes": 12},
      "paediatric": {"capacity": 12, "patients": 4, "wait_minutes": 9}
    },
    "doctors_on_shift": 14,
    "nurses_on_shift": 36,
    "parking_pct_full": 87,
    "nearest_carpark_miles": 0.2,
    "public_transport": "Bus 42 (2 mins) or Taxi (4 mins, est. £8)",
    "rating": 4.3,
    "wait_accuracy_pct": 91,
    "diverting": false,
    "notes": "",
    "languages_supported": ["English", "Urdu", "Polish", "Arabic", "Spanish"],
    "accessibility": ["wheelchair", "hearing-loop", "step-free", "interpreter-on-call"]
  },
  {
    "id": "MRI",
    "name": "Manchester Royal Infirmary",
    "trust": "Manchester University NHS Foundation Trust",
    "address": "Oxford Rd, Manchester M13 9WL",
    "lat": 53.4625,
    "lon": -2.2249,
    "specialties": ["general", "trauma", "cardiac", "stroke"],
    "departments": {
      "trauma":   {"capacity": 14, "patients": 12, "wait_minutes": 28},
      "cardiac":  {"capacity": 12, "patients": 11, "wait_minutes": 22},
      "general":  {"capacity": 60, "patients": 54, "wait_minutes": 41},
      "stroke":   {"capacity": 8,  "patients": 5,  "wait_minutes": 16}
    },
    "doctors_on_shift": 18,
    "nurses_on_shift": 44,
    "parking_pct_full": 95,
    "nearest_carpark_miles": 0.4,
    "public_transport": "Bus 41/42 frequent; Piccadilly tram 12 mins",
    "rating": 4.1,
    "wait_accuracy_pct": 84,
    "diverting": false,
    "notes": "Cardiac unit running near capacity",
    "languages_supported": ["English", "Urdu", "Polish", "Cantonese"],
    "accessibility": ["wheelchair", "hearing-loop", "step-free"]
  },
  {
    "id": "NMGH",
    "name": "North Manchester General Hospital",
    "trust": "Manchester University NHS Foundation Trust",
    "address": "Delaunays Rd, Crumpsall, Manchester M8 5RB",
    "lat": 53.5181,
    "lon": -2.2186,
    "specialties": ["general", "trauma", "mental-health"],
    "departments": {
      "trauma":   {"capacity": 8,  "patients": 4,  "wait_minutes": 11},
      "general":  {"capacity": 48, "patients": 22, "wait_minutes": 14},
      "mental-health": {"capacity": 16, "patients": 9, "wait_minutes": 22}
    },
    "doctors_on_shift": 11,
    "nurses_on_shift": 28,
    "parking_pct_full": 42,
    "nearest_carpark_miles": 0.1,
    "public_transport": "Bus 135 every 8 mins from city centre",
    "rating": 3.9,
    "wait_accuracy_pct": 88,
    "diverting": false,
    "notes": "",
    "languages_supported": ["English", "Urdu", "Punjabi"],
    "accessibility": ["wheelchair", "step-free"]
  },
  {
    "id": "WYTH",
    "name": "Wythenshawe Hospital",
    "trust": "Manchester University NHS Foundation Trust",
    "address": "Southmoor Rd, Wythenshawe, Manchester M23 9LT",
    "lat": 53.3895,
    "lon": -2.2917,
    "specialties": ["general", "cardiac", "respiratory", "transplant"],
    "departments": {
      "cardiac":  {"capacity": 14, "patients": 8,  "wait_minutes": 17},
      "respiratory": {"capacity": 12, "patients": 6, "wait_minutes": 13},
      "general":  {"capacity": 50, "patients": 31, "wait_minutes": 19}
    },
    "doctors_on_shift": 15,
    "nurses_on_shift": 38,
    "parking_pct_full": 61,
    "nearest_carpark_miles": 0.05,
    "public_transport": "Metrolink Wythenshawe Hospital stop on-site",
    "rating": 4.4,
    "wait_accuracy_pct": 93,
    "diverting": false,
    "notes": "Specialist heart and lung centre",
    "languages_supported": ["English", "Urdu", "Polish", "Romanian"],
    "accessibility": ["wheelchair", "hearing-loop", "step-free", "sensory-room"]
  },
  {
    "id": "SALFORD",
    "name": "Salford Royal Hospital",
    "trust": "Northern Care Alliance NHS Foundation Trust",
    "address": "Stott Ln, Salford M6 8HD",
    "lat": 53.4881,
    "lon": -2.3192,
    "specialties": ["general", "trauma", "neuro", "stroke"],
    "departments": {
      "trauma":   {"capacity": 12, "patients": 9,  "wait_minutes": 21},
      "neuro":    {"capacity": 10, "patients": 5,  "wait_minutes": 15},
      "stroke":   {"capacity": 10, "patients": 6,  "wait_minutes": 12},
      "general":  {"capacity": 46, "patients": 19, "wait_minutes": 11}
    },
    "doctors_on_shift": 13,
    "nurses_on_shift": 32,
    "parking_pct_full": 55,
    "nearest_carpark_miles": 0.1,
    "public_transport": "Bus 36, 50 every 6 mins",
    "rating": 4.5,
    "wait_accuracy_pct": 95,
    "diverting": false,
    "notes": "Major Trauma Centre & specialist neurosciences",
    "languages_supported": ["English", "Urdu", "Polish", "BSL"],
    "accessibility": ["wheelchair", "hearing-loop", "step-free", "BSL-on-call"]
  },
  {
    "id": "TRAFFORD",
    "name": "Trafford General Hospital",
    "trust": "Manchester University NHS Foundation Trust",
    "address": "Moorside Rd, Davyhulme, Manchester M41 5SL",
    "lat": 53.4502,
    "lon": -2.3679,
    "specialties": ["general", "urgent-care", "rehabilitation"],
    "departments": {
      "general":  {"capacity": 36, "patients": 12, "wait_minutes": 8},
      "urgent-care": {"capacity": 24, "patients": 7, "wait_minutes": 6}
    },
    "doctors_on_shift": 8,
    "nurses_on_shift": 19,
    "parking_pct_full": 31,
    "nearest_carpark_miles": 0.05,
    "public_transport": "Bus 25 every 12 mins",
    "rating": 4.0,
    "wait_accuracy_pct": 90,
    "diverting": false,
    "notes": "Urgent care unit — not full A&E for major trauma",
    "languages_supported": ["English", "Polish"],
    "accessibility": ["wheelchair", "step-free"]
  },
  {
    "id": "STEPHENS",
    "name": "Stepping Hill Hospital",
    "trust": "Stockport NHS Foundation Trust",
    "address": "Poplar Grove, Stockport SK2 7JE",
    "lat": 53.3856,
    "lon": -2.1409,
    "specialties": ["general", "cardiac", "paediatric"],
    "departments": {
      "cardiac":  {"capacity": 10, "patients": 7,  "wait_minutes": 19},
      "paediatric": {"capacity": 14, "patients": 5, "wait_minutes": 11},
      "general":  {"capacity": 44, "patients": 26, "wait_minutes": 17}
    },
    "doctors_on_shift": 10,
    "nurses_on_shift": 26,
    "parking_pct_full": 70,
    "nearest_carpark_miles": 0.1,
    "public_transport": "Bus 192 every 5 mins from Manchester",
    "rating": 4.2,
    "wait_accuracy_pct": 89,
    "diverting": false,
    "notes": "",
    "languages_supported": ["English", "Urdu", "Polish"],
    "accessibility": ["wheelchair", "hearing-loop", "step-free"]
  },
  {
    "id": "TAMESIDE",
    "name": "Tameside General Hospital",
    "trust": "Tameside and Glossop Integrated Care NHS FT",
    "address": "Fountain St, Ashton-under-Lyne OL6 9RW",
    "lat": 53.4878,
    "lon": -2.0863,
    "specialties": ["general", "urgent-care"],
    "departments": {
      "general":  {"capacity": 38, "patients": 35, "wait_minutes": 52},
      "urgent-care": {"capacity": 18, "patients": 16, "wait_minutes": 38}
    },
    "doctors_on_shift": 7,
    "nurses_on_shift": 18,
    "parking_pct_full": 88,
    "nearest_carpark_miles": 0.15,
    "public_transport": "Bus 219 every 10 mins",
    "rating": 3.6,
    "wait_accuracy_pct": 78,
    "diverting": true,
    "notes": "Diverting non-critical cases — CT scanner intermittent",
    "languages_supported": ["English"],
    "accessibility": ["wheelchair", "step-free"]
  }
]
